progrich/__init__.py
progrich/fmt.py
progrich/manager.py
progrich/pbar.py
progrich/signal_handler.py
progrich/spinner.py
progrich/table.py
progrich/widget.py
progrich/columns/__init__.py
progrich/columns/completion_ratio.py
progrich/columns/elapsed.py
progrich/columns/eta.py
progrich/columns/speed.py
progrich/columns/utils.py
progrich-0.2.0.dist-info/METADATA
progrich-0.2.0.dist-info/WHEEL
progrich-0.2.0.dist-info/licenses/LICENSE
progrich-0.2.0.dist-info/RECORD
