Metadata-Version: 2.4
Name: progrich
Version: 0.2.0
Summary: Progress bars, spinners and other widgets from rich made more intuitive, including more sensible defaults.
Author-email: Michael Jungo <michaeljungo92@gmail.com>
License-File: LICENSE
Requires-Python: >=3.12
Requires-Dist: rich>=14.0.0
